cegalprizm/hub/__init__.py
cegalprizm/hub/agent.py
cegalprizm/hub/agent_pb2.py
cegalprizm/hub/agent_pb2_grpc.py
cegalprizm/hub/base_ctx.py
cegalprizm/hub/capability.py
cegalprizm/hub/client.py
cegalprizm/hub/client_config.py
cegalprizm/hub/connection_parameters.py
cegalprizm/hub/connector.py
cegalprizm/hub/connector_filter.py
cegalprizm/hub/connector_request_service_pb2.py
cegalprizm/hub/connector_request_service_pb2_grpc.py
cegalprizm/hub/connector_task_service_pb2.py
cegalprizm/hub/connector_task_service_pb2_grpc.py
cegalprizm/hub/generic_client_interceptor.py
cegalprizm/hub/hub.py
cegalprizm/hub/hub_channel.py
cegalprizm/hub/impersonation_interceptor.py
cegalprizm/hub/keystone_auth_interceptor.py
cegalprizm/hub/payload_auth.py
cegalprizm/hub/petrel.py
cegalprizm/hub/petrel_pb2.py
cegalprizm/hub/petrel_pb2_grpc.py
cegalprizm/hub/server_config.py
cegalprizm/hub/server_service_pb2.py
cegalprizm/hub/server_service_pb2_grpc.py
cegalprizm/hub/task_registry.py
cegalprizm/hub/threadsafe.py
cegalprizm_hub-1.2.4.dist-info/LICENSE
cegalprizm_hub-1.2.4.dist-info/METADATA
cegalprizm_hub-1.2.4.dist-info/WHEEL
cegalprizm_hub-1.2.4.dist-info/top_level.txt
cegalprizm_hub-1.2.4.dist-info/RECORD
