Metadata-Version: 2.1
Name: cegalprizm-hub
Version: 1.2.4
Summary: A Python package to interact with a Cegal Hub Server and Cegal Hub Connectors
Home-page: https://docs.prizm.cegal-geo.com/
Author: Cegal Prizm Team
Author-email: prizm@cegal.com
Classifier: Programming Language :: Python :: 3
Classifier: License :: Other/Proprietary License
Classifier: Operating System :: OS Independent
Requires-Python: >=3.6
License-File: LICENSE
Requires-Dist: packaging >=21.0
Requires-Dist: grpcio >=1.33.2
Requires-Dist: protobuf <4,>=3
Requires-Dist: cegal-keystoneauth <2,>=1.0.14
